{
    "key_map": {
        "id": 0,
        "event_reward_type": 1,
        "event_reward_value": 2,
        "event_reward_size": 3,
        "description": 4
    },
    "data": [
        [
            1,
            6,
            63,
            2,
            "【#hero#】巡逻中，遇见一个太监，见他神色慌张，从他身上搜出#reward#"
        ],
        [
            2,
            6,
            63,
            5,
            "【#hero#】见青楼老鸨正在街上逼良为娼，救出美人，美人赠你#reward#"
        ],
        [
            3,
            6,
            64,
            1,
            "【#hero#】搀扶一个老太太过马路，获赠#reward#"
        ],
        [
            4,
            6,
            64,
            3,
            "一女子跳水，【#hero#】奋勇将其救起，获美人相赠#reward#"
        ],
        [
            5,
            6,
            2,
            1,
            "【#hero#】遇见一队商人，征收税金获得#reward#"
        ],
        [
            6,
            5,
            2,
            10000,
            "【#hero#】巡逻中，见一牌子插于地面，上写此处有银两，刨开地面获得#reward#"
        ],
        [
            7,
            5,
            2,
            20000,
            "【#hero#】抓住一小偷，从小偷身上搜出#reward#"
        ],
        [
            8,
            5,
            2,
            50000,
            "【#hero#】在赌场赌石，运气好，盈利#reward#"
        ],
        [
            9,
            5,
            9,
            50,
            "【#hero#】看见一山洞，好奇进去，发现此乃先人墓地，从此处获得#reward#"
        ],
        [
            10,
            5,
            9,
            100,
            "【#hero#】救下一队正在被歹徒打劫的商队，获赠#reward#"
        ],
        [
            11,
            5,
            1,
            5,
            "【#hero#】帮助城里达官显贵盖建新屋，获赠#reward#"
        ],
        [
            12,
            5,
            1,
            50,
            "【#hero#】见一富贵老太太被歹徒欺凌，奋勇上前惩治歹徒，获赠#reward#"
        ],
        [
            13,
            6,
            73,
            2,
            "【#hero#】遇见一得道高僧，高僧见其骨骼精奇，赠从#reward#"
        ],
        [
            14,
            6,
            73,
            5,
            "【#hero#】由于一算命先生，看你面向和善，赠送#reward#"
        ],
        [
            15,
            6,
            74,
            1,
            "【#hero#】见到一凯旋归来的将军，两人相谈甚欢，获赠#reward#"
        ],
        [
            16,
            6,
            74,
            3,
            "【#hero#】寻得一处宝山，从此山中挖出#reward#"
        ],
        [
            17,
            6,
            2,
            1,
            "【#hero#】遇见一队商人，征收税金获得#reward#"
        ],
        [
            18,
            5,
            2,
            10000,
            "【#hero#】巡逻中，见一牌子插于地面，上写此处有银两，刨开地面获得#reward#"
        ],
        [
            19,
            5,
            2,
            20000,
            "【#hero#】抓住一小偷，从小偷身上搜出#reward#"
        ],
        [
            20,
            5,
            2,
            50000,
            "【#hero#】在赌场赌石，运气好，盈利#reward#"
        ],
        [
            21,
            5,
            9,
            40,
            "【#hero#】见一人在被算命的骗财，上前相助后，获赠#reward#"
        ],
        [
            22,
            5,
            9,
            100,
            "【#hero#】听说城里一座山上有个庙很灵，去拜访后，获得#reward#"
        ],
        [
            23,
            5,
            1,
            5,
            "【#hero#】帮助城里达官显贵盖建新屋，获赠#reward#"
        ],
        [
            24,
            5,
            1,
            50,
            "【#hero#】见一富贵老太太被歹徒欺凌，奋勇上前惩治歹徒，获赠#reward#"
        ],
        [
            25,
            6,
            3,
            10,
            "【#hero#】修炼时有所感悟，将自身真气凝结成#reward#"
        ],
        [
            26,
            6,
            3,
            20,
            "【#hero#】酒馆中和人喝酒畅谈，那人谈到兴起，将修炼秘诀告知，并赠送#reward#"
        ],
        [
            27,
            6,
            3,
            40,
            "【#hero#】帮助铁匠打磨工具，获赠#reward#"
        ],
        [
            28,
            6,
            3,
            80,
            "铁匠家女儿在比武招亲，【#hero#】兴起参加，获得奖励#reward#"
        ],
        [
            29,
            6,
            2,
            1,
            "【#hero#】遇见一队商人，征收税金获得#reward#"
        ],
        [
            30,
            5,
            2,
            10000,
            "【#hero#】巡逻中，见一牌子插于地面，上写此处有银两，刨开地面获得#reward#"
        ],
        [
            31,
            5,
            2,
            20000,
            "【#hero#】抓住一小偷，从小偷身上搜出#reward#"
        ],
        [
            32,
            5,
            2,
            50000,
            "【#hero#】在赌场赌石，运气好，盈利#reward#"
        ],
        [
            33,
            5,
            9,
            40,
            "【#hero#】看见一山洞，好奇进去，发现此乃先人墓地，从此处获得#reward#"
        ],
        [
            34,
            5,
            9,
            100,
            "【#hero#】救下一队正在被歹徒打劫的商队，获赠#reward#"
        ],
        [
            35,
            5,
            1,
            5,
            "【#hero#】帮助城里达官显贵盖建新屋，获赠#reward#"
        ],
        [
            36,
            5,
            1,
            50,
            "【#hero#】见一富贵老太太被歹徒欺凌，奋勇上前惩治歹徒，获赠#reward#"
        ],
        [
            37,
            6,
            13,
            2,
            "铁匠家女儿在比武招亲，【#hero#】兴起参加，获得奖励#reward#"
        ],
        [
            38,
            6,
            13,
            4,
            "【#hero#】帮助铁匠打磨工具，获赠#reward#"
        ],
        [
            39,
            5,
            10,
            100,
            "【#hero#】救起一醉酒落水女子，恰为铁匠女儿，获赠#reward#"
        ],
        [
            40,
            5,
            10,
            300,
            "【#hero#】在山中偶然获得一块矿石，经过锤炼获得#reward#"
        ],
        [
            41,
            6,
            2,
            1,
            "【#hero#】遇见一队商人，征收税金获得#reward#"
        ],
        [
            42,
            5,
            2,
            10000,
            "【#hero#】巡逻中，见一牌子插于地面，上写此处有银两，刨开地面获得#reward#"
        ],
        [
            43,
            5,
            2,
            20000,
            "【#hero#】抓住一小偷，从小偷身上搜出#reward#"
        ],
        [
            44,
            5,
            2,
            50000,
            "【#hero#】在赌场赌石，运气好，盈利#reward#"
        ],
        [
            45,
            5,
            9,
            40,
            "【#hero#】与人打赌，幸运赢了，获得#reward#"
        ],
        [
            46,
            5,
            9,
            200,
            "【#hero#】帮助铁匠打磨工具，获赠#reward#"
        ],
        [
            47,
            5,
            1,
            5,
            "【#hero#】帮助城里达官显贵盖建新屋，获赠#reward#"
        ],
        [
            48,
            5,
            1,
            50,
            "【#hero#】见一富贵老太太被歹徒欺凌，奋勇上前惩治歹徒，获赠#reward#"
        ],
        [
            49,
            6,
            10,
            20,
            "【#hero#】与人切磋，胜利后获得那人赏识，并获赠#reward#"
        ],
        [
            50,
            6,
            10,
            50,
            "【#hero#】在书馆里认真钻研文学，获得店家赠送#reward#"
        ],
        [
            51,
            5,
            17,
            150,
            "【#hero#】帮助一位大妈找回丢失的小狗，获赠#reward#"
        ],
        [
            52,
            5,
            17,
            300,
            "【#hero#】见到一盗墓贼，将其擒获，并从其身上搜出#reward#"
        ],
        [
            53,
            6,
            2,
            1,
            "【#hero#】搀扶一个老太太过马路，获赠#reward#"
        ],
        [
            54,
            5,
            2,
            10000,
            "一女子跳水，【#hero#】奋勇将其救起，获美人相赠#reward#"
        ],
        [
            55,
            5,
            2,
            20000,
            "【#hero#】遇见一队商人，征收税金获得#reward#"
        ],
        [
            56,
            5,
            2,
            50000,
            "【#hero#】巡逻中，见一牌子插于地面，上写此处有银两，刨开地面获得#reward#"
        ],
        [
            57,
            5,
            9,
            40,
            "【#hero#】见到一盗墓贼，将其擒获，并从其身上搜出#reward#"
        ],
        [
            58,
            5,
            9,
            200,
            "【#hero#】与人切磋，胜利后获得那人赏识，并获赠#reward#"
        ],
        [
            59,
            5,
            1,
            5,
            "【#hero#】帮助城里达官显贵盖建新屋，获赠#reward#"
        ],
        [
            60,
            5,
            1,
            80,
            "【#hero#】见一富贵老太太被歹徒欺凌，奋勇上前惩治歹徒，获赠#reward#"
        ],
        [
            61,
            6,
            19,
            20,
            "【#hero#】听说附近有神兵出土，一时好奇，前去寻找，意外获得#reward#"
        ],
        [
            62,
            6,
            19,
            50,
            "【#hero#】抓住一小偷，从小偷身上搜出#reward#"
        ],
        [
            63,
            5,
            8,
            100,
            "【#hero#】在拳击场上奋勇杀敌，获赠奖励#reward#"
        ],
        [
            64,
            5,
            8,
            300,
            "【#hero#】看见一美女，被色狼非礼，上去施救，恰巧为城主女儿，获赠奖励#reward#"
        ],
        [
            65,
            6,
            2,
            1,
            "【#hero#】搀扶一个老太太过马路，获赠#reward#"
        ],
        [
            66,
            5,
            2,
            10000,
            "一女子跳水，【#hero#】奋勇将其救起，获美人相赠#reward#"
        ],
        [
            67,
            5,
            2,
            20000,
            "【#hero#】遇见一队商人，征收税金获得#reward#"
        ],
        [
            68,
            5,
            2,
            50000,
            "【#hero#】巡逻中，见一牌子插于地面，上写此处有银两，刨开地面获得#reward#"
        ],
        [
            69,
            5,
            9,
            40,
            "铁匠家女儿在比武招亲，【#hero#】兴起参加，获得奖励#reward#"
        ],
        [
            70,
            5,
            9,
            200,
            "【#hero#】看见一山洞，好奇进去，发现此乃先人墓地，从此处获得#reward#"
        ],
        [
            71,
            5,
            1,
            5,
            "【#hero#】帮助城里达官显贵盖建新屋，获赠#reward#"
        ],
        [
            72,
            5,
            1,
            50,
            "【#hero#】见一富贵老太太被歹徒欺凌，奋勇上前惩治歹徒，获赠#reward#"
        ],
        [
            73,
            0,
            0,
            0,
            "驻扎4小时后，【#hero#】完成了驻扎任务，获得了#reward#"
        ],
        [
            74,
            0,
            0,
            0,
            "驻扎8小时后，【#hero#】完成了驻扎任务，获得了#reward#"
        ],
        [
            75,
            0,
            0,
            0,
            "驻扎12小时后，【#hero#】完成了驻扎任务，获得了#reward#"
        ]
    ],
    "indexes": {
        "1": 0,
        "2": 1,
        "3": 2,
        "4": 3,
        "5": 4,
        "6": 5,
        "7": 6,
        "8": 7,
        "9": 8,
        "10": 9,
        "11": 10,
        "12": 11,
        "13": 12,
        "14": 13,
        "15": 14,
        "16": 15,
        "17": 16,
        "18": 17,
        "19": 18,
        "20": 19,
        "21": 20,
        "22": 21,
        "23": 22,
        "24": 23,
        "25": 24,
        "26": 25,
        "27": 26,
        "28": 27,
        "29": 28,
        "30": 29,
        "31": 30,
        "32": 31,
        "33": 32,
        "34": 33,
        "35": 34,
        "36": 35,
        "37": 36,
        "38": 37,
        "39": 38,
        "40": 39,
        "41": 40,
        "42": 41,
        "43": 42,
        "44": 43,
        "45": 44,
        "46": 45,
        "47": 46,
        "48": 47,
        "49": 48,
        "50": 49,
        "51": 50,
        "52": 51,
        "53": 52,
        "54": 53,
        "55": 54,
        "56": 55,
        "57": 56,
        "58": 57,
        "59": 58,
        "60": 59,
        "61": 60,
        "62": 61,
        "63": 62,
        "64": 63,
        "65": 64,
        "66": 65,
        "67": 66,
        "68": 67,
        "69": 68,
        "70": 69,
        "71": 70,
        "72": 71,
        "73": 72,
        "74": 73,
        "75": 74
    }
}